n8py/__init__.py
n8py/core.py
n8py/data/0.txt
n8py/data/1.txt
n8py/data/11.txt
n8py/data/12.txt
n8py/data/13.txt
n8py/data/14.txt
n8py/data/15.txt
n8py/data/2.txt
n8py/data/3.txt
n8py/data/4.txt
n8py/data/5.txt
n8py/data/6.txt
n8py/data/7.txt
n8py/data/8.txt
n8py-3.2.4.dist-info/METADATA
n8py-3.2.4.dist-info/WHEEL
n8py-3.2.4.dist-info/top_level.txt
n8py-3.2.4.dist-info/RECORD
